{"cameraMode":{"drawMode":0,"name":"Shaded","section":"Shading Mode"},"sceneLighting":true,"audioPlay":false,"sceneViewState":{"m_AlwaysRefresh":false,"showFog":true,"showSkybox":true,"showFlares":true,"showImageEffects":true,"showParticleSystems":true,"showVisualEffectGraphs":true,"m_FxEnabled":true},"in2DMode":false,"pivot":{"x":-3.4993982315063478,"y":1.057295799255371,"z":106.47042846679688},"rotation":{"x":0.04853062704205513,"y":-0.708581805229187,"z":0.048969853669404986,"w":0.702233076095581},"size":0.8660364747047424,"orthographic":false}